{
  "version": "1.0.0",
  "cam_reference": {
    "cam_version": "1.0.0",
    "board": "ICSE",
    "class": 5,
    "subject": "Mathematics"
  },
  "topic_id": "T07.03",
  "topic_name": "Capacity/Volume",
  "canonical_explanation": {
    "text": "Capacity measures how much liquid a container can hold. The metric system uses milliliters (ml) and liters (l). To convert liters to milliliters, multiply by 1000. To convert milliliters to liters, divide by 1000.",
    "rules": [
      "1 l = 1000 ml",
      "l to ml: multiply by 1000",
      "ml to l: divide by 1000",
      "Measuring jug is used to measure liquids"
    ]
  },
  "questions": [
    {
      "question_id": "T07.03.Q001",
      "concept_id": "T07.03.C01",
      "difficulty": "familiarity",
      "type": "mcq",
      "question_text": "How many milliliters are in 1 liter?",
      "options": [
        {
          "id": "A",
          "text": "10"
        },
        {
          "id": "B",
          "text": "100"
        },
        {
          "id": "C",
          "text": "1000"
        },
        {
          "id": "D",
          "text": "10000"
        }
      ],
      "correct_answer": "C"
    },
    {
      "question_id": "T07.03.Q002",
      "concept_id": "T07.03.C02",
      "difficulty": "familiarity",
      "type": "fill_blank",
      "question_text": "4 l = ___ ml",
      "correct_answer": "4000"
    },
    {
      "question_id": "T07.03.Q003",
      "concept_id": "T07.03.C02",
      "difficulty": "application",
      "type": "mcq",
      "question_text": "Convert 2,500 ml to liters:",
      "options": [
        {
          "id": "A",
          "text": "0.25 l"
        },
        {
          "id": "B",
          "text": "2.5 l"
        },
        {
          "id": "C",
          "text": "25 l"
        },
        {
          "id": "D",
          "text": "250 l"
        }
      ],
      "correct_answer": "B"
    },
    {
      "question_id": "T07.03.Q004",
      "concept_id": "T07.03.C01",
      "difficulty": "familiarity",
      "type": "mcq",
      "question_text": "Which unit would you use to measure the capacity of a bathtub?",
      "options": [
        {
          "id": "A",
          "text": "Milliliters"
        },
        {
          "id": "B",
          "text": "Liters"
        },
        {
          "id": "C",
          "text": "Grams"
        },
        {
          "id": "D",
          "text": "Meters"
        }
      ],
      "correct_answer": "B"
    },
    {
      "question_id": "T07.03.Q005",
      "concept_id": "T07.03.C03",
      "difficulty": "familiarity",
      "type": "mcq",
      "question_text": "Which instrument is used to measure the capacity of liquids?",
      "options": [
        {
          "id": "A",
          "text": "Ruler"
        },
        {
          "id": "B",
          "text": "Balance"
        },
        {
          "id": "C",
          "text": "Measuring jug"
        },
        {
          "id": "D",
          "text": "Thermometer"
        }
      ],
      "correct_answer": "C"
    },
    {
      "question_id": "T07.03.Q006",
      "concept_id": "T07.03.C04",
      "difficulty": "application",
      "type": "mcq",
      "question_text": "A teaspoon holds about:",
      "options": [
        {
          "id": "A",
          "text": "5 ml"
        },
        {
          "id": "B",
          "text": "50 ml"
        },
        {
          "id": "C",
          "text": "500 ml"
        },
        {
          "id": "D",
          "text": "5 l"
        }
      ],
      "correct_answer": "A"
    },
    {
      "question_id": "T07.03.Q007",
      "concept_id": "T07.03.C02",
      "difficulty": "application",
      "type": "mcq",
      "question_text": "3 l 250 ml = ___ ml",
      "options": [
        {
          "id": "A",
          "text": "3,025 ml"
        },
        {
          "id": "B",
          "text": "3,250 ml"
        },
        {
          "id": "C",
          "text": "32,500 ml"
        },
        {
          "id": "D",
          "text": "325 ml"
        }
      ],
      "correct_answer": "B"
    },
    {
      "question_id": "T07.03.Q008",
      "concept_id": "T07.03.C05",
      "difficulty": "application",
      "type": "mcq",
      "question_text": "A bottle contains 1 l 500 ml of juice. Another bottle contains 2 l 750 ml. What is the total?",
      "options": [
        {
          "id": "A",
          "text": "3 l 250 ml"
        },
        {
          "id": "B",
          "text": "4 l 250 ml"
        },
        {
          "id": "C",
          "text": "3 l 1250 ml"
        },
        {
          "id": "D",
          "text": "4 l 150 ml"
        }
      ],
      "correct_answer": "B"
    },
    {
      "question_id": "T07.03.Q009",
      "concept_id": "T07.03.C05",
      "difficulty": "exam_style",
      "type": "mcq",
      "question_text": "A tank has 25 l of water. If 8 l 350 ml is used, how much is left?",
      "options": [
        {
          "id": "A",
          "text": "16 l 650 ml"
        },
        {
          "id": "B",
          "text": "17 l 650 ml"
        },
        {
          "id": "C",
          "text": "16 l 350 ml"
        },
        {
          "id": "D",
          "text": "17 l 350 ml"
        }
      ],
      "correct_answer": "A"
    },
    {
      "question_id": "T07.03.Q010",
      "concept_id": "T07.03.C01",
      "difficulty": "application",
      "type": "mcq",
      "question_text": "Which is more: 1,800 ml or 2 l?",
      "options": [
        {
          "id": "A",
          "text": "1,800 ml"
        },
        {
          "id": "B",
          "text": "2 l"
        },
        {
          "id": "C",
          "text": "Both are equal"
        },
        {
          "id": "D",
          "text": "Cannot compare"
        }
      ],
      "correct_answer": "B"
    },
    {
      "question_id": "T07.03.Q011",
      "concept_id": "T07.03.C05",
      "difficulty": "exam_style",
      "type": "mcq",
      "question_text": "A bucket holds 15 l. How many 500 ml bottles can be filled from it?",
      "options": [
        {
          "id": "A",
          "text": "15"
        },
        {
          "id": "B",
          "text": "30"
        },
        {
          "id": "C",
          "text": "3"
        },
        {
          "id": "D",
          "text": "150"
        }
      ],
      "correct_answer": "B"
    },
    {
      "question_id": "T07.03.Q012",
      "concept_id": "T07.03.C04",
      "difficulty": "familiarity",
      "type": "mcq",
      "question_text": "A standard water bottle holds about:",
      "options": [
        {
          "id": "A",
          "text": "1 ml"
        },
        {
          "id": "B",
          "text": "100 ml"
        },
        {
          "id": "C",
          "text": "500 ml"
        },
        {
          "id": "D",
          "text": "50 l"
        }
      ],
      "correct_answer": "C"
    },
    {
      "question_id": "T07.03.Q013",
      "concept_id": "T07.03.C02",
      "difficulty": "exam_style",
      "type": "fill_blank",
      "question_text": "6 l 75 ml = ___ ml",
      "correct_answer": "6075"
    },
    {
      "question_id": "T07.03.Q014",
      "concept_id": "T07.03.C05",
      "difficulty": "exam_style",
      "type": "mcq",
      "question_text": "Milk is sold in packets of 500 ml. How many packets are needed for 5 l?",
      "options": [
        {
          "id": "A",
          "text": "5"
        },
        {
          "id": "B",
          "text": "10"
        },
        {
          "id": "C",
          "text": "50"
        },
        {
          "id": "D",
          "text": "100"
        }
      ],
      "correct_answer": "B"
    },
    {
      "question_id": "T07.03.Q015",
      "concept_id": "T07.03.C03",
      "difficulty": "application",
      "type": "true_false",
      "question_text": "A beaker can be used to measure the volume of liquids.",
      "correct_answer": "true"
    },
    {
      "question_id": "T07.03.Q016",
      "concept_id": "T07.03.C01",
      "difficulty": "familiarity",
      "type": "mcq",
      "question_text": "The capacity of a container is measured in:",
      "options": [
        {
          "id": "A",
          "text": "Meters"
        },
        {
          "id": "B",
          "text": "Grams"
        },
        {
          "id": "C",
          "text": "Liters"
        },
        {
          "id": "D",
          "text": "Degrees"
        }
      ],
      "correct_answer": "C"
    },
    {
      "question_id": "T07.03.Q017",
      "concept_id": "T07.03.C01",
      "difficulty": "familiarity",
      "type": "true_false",
      "question_text": "1 liter = 100 milliliters.",
      "correct_answer": "false"
    },
    {
      "question_id": "T07.03.Q018",
      "concept_id": "T07.03.C02",
      "difficulty": "familiarity",
      "type": "fill_blank",
      "question_text": "7 l = ___ ml",
      "correct_answer": "7000"
    },
    {
      "question_id": "T07.03.Q019",
      "concept_id": "T07.03.C02",
      "difficulty": "application",
      "type": "mcq",
      "question_text": "Convert 3,500 ml to liters:",
      "options": [
        {
          "id": "A",
          "text": "0.35 l"
        },
        {
          "id": "B",
          "text": "3.5 l"
        },
        {
          "id": "C",
          "text": "35 l"
        },
        {
          "id": "D",
          "text": "350 l"
        }
      ],
      "correct_answer": "B"
    },
    {
      "question_id": "T07.03.Q020",
      "concept_id": "T07.03.C02",
      "difficulty": "application",
      "type": "fill_blank",
      "question_text": "2 l 750 ml = ___ ml",
      "correct_answer": "2750"
    },
    {
      "question_id": "T07.03.Q021",
      "concept_id": "T07.03.C02",
      "difficulty": "application",
      "type": "mcq",
      "question_text": "Express 4,125 ml in l and ml:",
      "options": [
        {
          "id": "A",
          "text": "4 l 125 ml"
        },
        {
          "id": "B",
          "text": "41 l 25 ml"
        },
        {
          "id": "C",
          "text": "4 l 25 ml"
        },
        {
          "id": "D",
          "text": "412 l 5 ml"
        }
      ],
      "correct_answer": "A"
    },
    {
      "question_id": "T07.03.Q022",
      "concept_id": "T07.03.C03",
      "difficulty": "familiarity",
      "type": "mcq",
      "question_text": "A graduated cylinder is used to:",
      "options": [
        {
          "id": "A",
          "text": "Measure temperature"
        },
        {
          "id": "B",
          "text": "Measure weight"
        },
        {
          "id": "C",
          "text": "Measure volume of liquids"
        },
        {
          "id": "D",
          "text": "Measure length"
        }
      ],
      "correct_answer": "C"
    },
    {
      "question_id": "T07.03.Q023",
      "concept_id": "T07.03.C04",
      "difficulty": "familiarity",
      "type": "mcq",
      "question_text": "A bucket typically holds about:",
      "options": [
        {
          "id": "A",
          "text": "10 ml"
        },
        {
          "id": "B",
          "text": "100 ml"
        },
        {
          "id": "C",
          "text": "10 l"
        },
        {
          "id": "D",
          "text": "100 l"
        }
      ],
      "correct_answer": "C"
    },
    {
      "question_id": "T07.03.Q025",
      "concept_id": "T07.03.C05",
      "difficulty": "application",
      "type": "mcq",
      "question_text": "Add: 4 l 350 ml + 2 l 780 ml",
      "options": [
        {
          "id": "A",
          "text": "6 l 1130 ml"
        },
        {
          "id": "B",
          "text": "7 l 130 ml"
        },
        {
          "id": "C",
          "text": "6 l 130 ml"
        },
        {
          "id": "D",
          "text": "7 l 30 ml"
        }
      ],
      "correct_answer": "B"
    },
    {
      "question_id": "T07.03.Q026",
      "concept_id": "T07.03.C05",
      "difficulty": "application",
      "type": "mcq",
      "question_text": "Subtract: 9 l 200 ml - 3 l 650 ml",
      "options": [
        {
          "id": "A",
          "text": "5 l 550 ml"
        },
        {
          "id": "B",
          "text": "6 l 450 ml"
        },
        {
          "id": "C",
          "text": "5 l 450 ml"
        },
        {
          "id": "D",
          "text": "6 l 550 ml"
        }
      ],
      "correct_answer": "A"
    },
    {
      "question_id": "T07.03.Q027",
      "concept_id": "T07.03.C01",
      "difficulty": "application",
      "type": "mcq",
      "question_text": "Arrange in ascending order: 500 ml, 5 l, 50 ml",
      "options": [
        {
          "id": "A",
          "text": "500 ml, 50 ml, 5 l"
        },
        {
          "id": "B",
          "text": "50 ml, 500 ml, 5 l"
        },
        {
          "id": "C",
          "text": "5 l, 500 ml, 50 ml"
        },
        {
          "id": "D",
          "text": "50 ml, 5 l, 500 ml"
        }
      ],
      "correct_answer": "B"
    },
    {
      "question_id": "T07.03.Q028",
      "concept_id": "T07.03.C02",
      "difficulty": "application",
      "type": "true_false",
      "question_text": "To convert milliliters to liters, we multiply by 1000.",
      "correct_answer": "false"
    },
    {
      "question_id": "T07.03.Q029",
      "concept_id": "T07.03.C05",
      "difficulty": "exam_style",
      "type": "mcq",
      "question_text": "A drum contains 200 l of water. If 20 buckets of 8 l each are filled, how much water is left?",
      "options": [
        {
          "id": "A",
          "text": "40 l"
        },
        {
          "id": "B",
          "text": "60 l"
        },
        {
          "id": "C",
          "text": "80 l"
        },
        {
          "id": "D",
          "text": "100 l"
        }
      ],
      "correct_answer": "A"
    },
    {
      "question_id": "T07.03.Q030",
      "concept_id": "T07.03.C05",
      "difficulty": "exam_style",
      "type": "mcq",
      "question_text": "Multiply: 2 l 450 ml ร 3",
      "options": [
        {
          "id": "A",
          "text": "6 l 1350 ml"
        },
        {
          "id": "B",
          "text": "7 l 350 ml"
        },
        {
          "id": "C",
          "text": "6 l 350 ml"
        },
        {
          "id": "D",
          "text": "7 l 150 ml"
        }
      ],
      "correct_answer": "B"
    },
    {
      "question_id": "T07.03.Q031",
      "concept_id": "T07.03.C05",
      "difficulty": "exam_style",
      "type": "mcq",
      "question_text": "A water tank holds 50 l. If 12 l 750 ml is used, how much water is left?",
      "options": [
        {
          "id": "A",
          "text": "37 l 250 ml"
        },
        {
          "id": "B",
          "text": "38 l 750 ml"
        },
        {
          "id": "C",
          "text": "37 l 750 ml"
        },
        {
          "id": "D",
          "text": "38 l 250 ml"
        }
      ],
      "correct_answer": "A"
    },
    {
      "question_id": "T07.03.Q032",
      "concept_id": "T07.03.C04",
      "difficulty": "familiarity",
      "type": "mcq",
      "question_text": "A glass of water holds approximately:",
      "options": [
        {
          "id": "A",
          "text": "25 ml"
        },
        {
          "id": "B",
          "text": "250 ml"
        },
        {
          "id": "C",
          "text": "2.5 l"
        },
        {
          "id": "D",
          "text": "25 l"
        }
      ],
      "correct_answer": "B"
    },
    {
      "question_id": "T07.03.Q033",
      "concept_id": "T07.03.C03",
      "difficulty": "familiarity",
      "type": "mcq",
      "question_text": "The markings on a measuring jug help us to:",
      "options": [
        {
          "id": "A",
          "text": "Know the weight"
        },
        {
          "id": "B",
          "text": "Read the exact volume"
        },
        {
          "id": "C",
          "text": "Know the temperature"
        },
        {
          "id": "D",
          "text": "Measure length"
        }
      ],
      "correct_answer": "B"
    },
    {
      "question_id": "T07.03.Q034",
      "concept_id": "T07.03.C02",
      "difficulty": "familiarity",
      "type": "fill_blank",
      "question_text": "5.5 l = ___ ml",
      "correct_answer": "5500"
    },
    {
      "question_id": "T07.03.Q035",
      "concept_id": "T07.03.C01",
      "difficulty": "application",
      "type": "mcq",
      "question_text": "Which is greater: 3 l or 2,900 ml?",
      "options": [
        {
          "id": "A",
          "text": "3 l"
        },
        {
          "id": "B",
          "text": "2,900 ml"
        },
        {
          "id": "C",
          "text": "Both are equal"
        },
        {
          "id": "D",
          "text": "Cannot compare"
        }
      ],
      "correct_answer": "A"
    },
    {
      "question_id": "T07.03.Q036",
      "concept_id": "T07.03.C05",
      "difficulty": "exam_style",
      "type": "mcq",
      "question_text": "Divide: 8 l 400 ml รท 4",
      "options": [
        {
          "id": "A",
          "text": "2 l 100 ml"
        },
        {
          "id": "B",
          "text": "2 l 10 ml"
        },
        {
          "id": "C",
          "text": "2 l 400 ml"
        },
        {
          "id": "D",
          "text": "2 l 1 ml"
        }
      ],
      "correct_answer": "A"
    },
    {
      "question_id": "T07.03.Q037",
      "concept_id": "T07.03.C04",
      "difficulty": "application",
      "type": "mcq",
      "question_text": "Which would you measure in milliliters?",
      "options": [
        {
          "id": "A",
          "text": "Water in a swimming pool"
        },
        {
          "id": "B",
          "text": "Medicine in a spoon"
        },
        {
          "id": "C",
          "text": "Petrol in a car tank"
        },
        {
          "id": "D",
          "text": "Water in a tank"
        }
      ],
      "correct_answer": "B"
    },
    {
      "question_id": "T07.03.Q038",
      "concept_id": "T07.03.C01",
      "difficulty": "familiarity",
      "type": "ordering",
      "question_text": "Arrange from smallest to largest capacity:",
      "items": [
        "100 ml",
        "10 ml",
        "1 l",
        "500 ml"
      ],
      "correct_answer": [
        "10 ml",
        "100 ml",
        "500 ml",
        "1 l"
      ]
    },
    {
      "question_id": "T07.03.Q039",
      "concept_id": "T07.03.C05",
      "difficulty": "exam_style",
      "type": "mcq",
      "question_text": "A juice concentrate is mixed with water in the ratio 1:4. If 200 ml of concentrate is used, how much water is needed?",
      "options": [
        {
          "id": "A",
          "text": "400 ml"
        },
        {
          "id": "B",
          "text": "600 ml"
        },
        {
          "id": "C",
          "text": "800 ml"
        },
        {
          "id": "D",
          "text": "1000 ml"
        }
      ],
      "correct_answer": "C"
    },
    {
      "question_id": "T07.03.Q040",
      "concept_id": "T07.03.C02",
      "difficulty": "application",
      "type": "mcq",
      "question_text": "Express 8,050 ml in l and ml:",
      "options": [
        {
          "id": "A",
          "text": "8 l 50 ml"
        },
        {
          "id": "B",
          "text": "80 l 50 ml"
        },
        {
          "id": "C",
          "text": "8 l 500 ml"
        },
        {
          "id": "D",
          "text": "805 l 0 ml"
        }
      ],
      "correct_answer": "A"
    },
    {
      "question_id": "T07.03.Q041",
      "concept_id": "T07.03.C03",
      "difficulty": "application",
      "type": "true_false",
      "question_text": "A syringe can be used to measure small volumes of liquid accurately.",
      "correct_answer": "true"
    },
    {
      "question_id": "T07.03.Q042",
      "concept_id": "T07.03.C05",
      "difficulty": "exam_style",
      "type": "mcq",
      "question_text": "A bottle contains 1.5 l of oil. How many 250 ml bottles can be filled?",
      "options": [
        {
          "id": "A",
          "text": "4"
        },
        {
          "id": "B",
          "text": "5"
        },
        {
          "id": "C",
          "text": "6"
        },
        {
          "id": "D",
          "text": "8"
        }
      ],
      "correct_answer": "C"
    },
    {
      "question_id": "T07.03.Q043",
      "concept_id": "T07.03.C04",
      "difficulty": "familiarity",
      "type": "mcq",
      "question_text": "A car's fuel tank holds approximately:",
      "options": [
        {
          "id": "A",
          "text": "5 l"
        },
        {
          "id": "B",
          "text": "50 l"
        },
        {
          "id": "C",
          "text": "500 l"
        },
        {
          "id": "D",
          "text": "5000 l"
        }
      ],
      "correct_answer": "B"
    },
    {
      "question_id": "T07.03.Q044",
      "concept_id": "T07.03.C02",
      "difficulty": "application",
      "type": "fill_blank",
      "question_text": "10 l 25 ml = ___ ml",
      "correct_answer": "10025"
    },
    {
      "question_id": "T07.03.Q045",
      "concept_id": "T07.03.C05",
      "difficulty": "exam_style",
      "type": "mcq",
      "question_text": "A family drinks 2 l 500 ml of milk daily. How much milk is consumed in a week?",
      "options": [
        {
          "id": "A",
          "text": "15 l 500 ml"
        },
        {
          "id": "B",
          "text": "17 l 500 ml"
        },
        {
          "id": "C",
          "text": "16 l 500 ml"
        },
        {
          "id": "D",
          "text": "14 l 500 ml"
        }
      ],
      "correct_answer": "B"
    },
    {
      "question_id": "T07.03.Q046",
      "concept_id": "T07.03.C01",
      "difficulty": "familiarity",
      "type": "true_false",
      "question_text": "Volume and capacity mean the same thing.",
      "correct_answer": "true"
    },
    {
      "question_id": "T07.03.Q047",
      "concept_id": "T07.03.C05",
      "difficulty": "exam_style",
      "type": "mcq",
      "question_text": "A tank contains 100 l of water. If 3/4 of it is used, how much remains?",
      "options": [
        {
          "id": "A",
          "text": "25 l"
        },
        {
          "id": "B",
          "text": "50 l"
        },
        {
          "id": "C",
          "text": "75 l"
        },
        {
          "id": "D",
          "text": "30 l"
        }
      ],
      "correct_answer": "A"
    },
    {
      "question_id": "T07.03.Q048",
      "concept_id": "T07.03.C04",
      "difficulty": "application",
      "type": "mcq",
      "question_text": "A tablespoon holds approximately:",
      "options": [
        {
          "id": "A",
          "text": "1 ml"
        },
        {
          "id": "B",
          "text": "15 ml"
        },
        {
          "id": "C",
          "text": "150 ml"
        },
        {
          "id": "D",
          "text": "1.5 l"
        }
      ],
      "correct_answer": "B"
    },
    {
      "question_id": "T07.03.Q049",
      "concept_id": "T07.03.C02",
      "difficulty": "exam_style",
      "type": "mcq",
      "question_text": "Express 15,250 ml in l and ml:",
      "options": [
        {
          "id": "A",
          "text": "15 l 250 ml"
        },
        {
          "id": "B",
          "text": "152 l 50 ml"
        },
        {
          "id": "C",
          "text": "1 l 5250 ml"
        },
        {
          "id": "D",
          "text": "15 l 25 ml"
        }
      ],
      "correct_answer": "A"
    },
    {
      "question_id": "T07.03.Q050",
      "concept_id": "T07.03.C05",
      "difficulty": "exam_style",
      "type": "mcq",
      "question_text": "A fruit punch recipe needs 1 l 250 ml of orange juice and 750 ml of mango juice. What is the total volume of juice?",
      "options": [
        {
          "id": "A",
          "text": "1 l 750 ml"
        },
        {
          "id": "B",
          "text": "2 l"
        },
        {
          "id": "C",
          "text": "2 l 250 ml"
        },
        {
          "id": "D",
          "text": "1 l 500 ml"
        }
      ],
      "correct_answer": "B"
    },
    {
      "question_id": "T07.03.Q051",
      "type": "mcq",
      "concept_id": "T07.03.C04",
      "difficulty": "application",
      "question_text": "What is the approximate capacity: of A cup of tea?",
      "options": [
        {
          "id": "A",
          "text": "50,000 l"
        },
        {
          "id": "B",
          "text": "5 ml"
        },
        {
          "id": "C",
          "text": "1 l"
        },
        {
          "id": "D",
          "text": "200 ml"
        }
      ],
      "correct_answer": "D"
    },
    {
      "question_id": "T07.03.Q052",
      "type": "mcq",
      "concept_id": "T07.03.C04",
      "difficulty": "application",
      "question_text": "What is the approximate capacity: of A large milk packet?",
      "options": [
        {
          "id": "A",
          "text": "50,000 l"
        },
        {
          "id": "B",
          "text": "5 ml"
        },
        {
          "id": "C",
          "text": "1 l"
        },
        {
          "id": "D",
          "text": "200 ml"
        }
      ],
      "correct_answer": "C"
    },
    {
      "question_id": "T07.03.Q053",
      "type": "mcq",
      "concept_id": "T07.03.C04",
      "difficulty": "application",
      "question_text": "What is the approximate capacity: of A swimming pool?",
      "options": [
        {
          "id": "A",
          "text": "5 ml"
        },
        {
          "id": "B",
          "text": "200 ml"
        },
        {
          "id": "C",
          "text": "50,000 l"
        },
        {
          "id": "D",
          "text": "1 l"
        }
      ],
      "correct_answer": "C"
    },
    {
      "question_id": "T07.03.Q054",
      "type": "mcq",
      "concept_id": "T07.03.C04",
      "difficulty": "application",
      "question_text": "What is the approximate capacity: of A medicine dropper?",
      "options": [
        {
          "id": "A",
          "text": "200 ml"
        },
        {
          "id": "B",
          "text": "50,000 l"
        },
        {
          "id": "C",
          "text": "1 l"
        },
        {
          "id": "D",
          "text": "5 ml"
        }
      ],
      "correct_answer": "D"
    }
  ],
  "metadata": {
    "created_at": "2026-01-07",
    "status": "draft",
    "question_count": {
      "total": 53,
      "by_difficulty": {
        "familiarity": 16,
        "application": 20,
        "exam_style": 14
      },
      "by_type": {
        "mcq": 41,
        "fill_blank": 6,
        "true_false": 5,
        "ordering": 1
      }
    }
  }
}